PySimpleGUIDesigner/README.md
PySimpleGUIDesigner/__init__.py
PySimpleGUIDesigner/__main__.py
PySimpleGUIDesigner/all_in_one_imports.py
PySimpleGUIDesigner/boilerplate_psg.py
PySimpleGUIDesigner/main.py
PySimpleGUIDesigner/main_for_devel.py
PySimpleGUIDesigner/psg_ui_maker.py
PySimpleGUIDesigner/real_src_here.py
PySimpleGUIDesigner/requirements.txt
PySimpleGUIDesigner/setting.json
PySimpleGUIDesigner/test.ui
PySimpleGUIDesigner/transpiler2.py
PySimpleGUIDesigner-0.1.4.7.dist-info/METADATA
PySimpleGUIDesigner-0.1.4.7.dist-info/WHEEL
PySimpleGUIDesigner-0.1.4.7.dist-info/entry_points.txt
PySimpleGUIDesigner-0.1.4.7.dist-info/top_level.txt
PySimpleGUIDesigner-0.1.4.7.dist-info/RECORD
