Metadata-Version: 2.1
Name: PySimpleGUIDesigner
Version: 0.1.4.7
Summary: PySimpleGUI designer, that uses transpiler to produce PySimpleGUI code from Qt Designer xml file.
Home-page: https://github.com/nngogol/PySimpleGUI_designer
Author: Nikolay Gogol
Author-email: nngogol09@gmail.com
License: GNU-GPL
Platform: UNKNOWN
Classifier: Programming Language :: Python :: 3
Classifier: Programming Language :: Python :: 3.6
Classifier: Programming Language :: Python :: 3.7
Classifier: Programming Language :: Python :: 3.8
Classifier: Topic :: Software Development :: Libraries :: Application Frameworks
Classifier: Topic :: Multimedia :: Graphics
Classifier: Operating System :: OS Independent
